scraping_common_bot/__init__.py
scraping_common_bot/file/__init__.py
scraping_common_bot/file/csv_manager.py
scraping_common_bot/scraping/__init__.py
scraping_common_bot/scraping/action/__init__.py
scraping_common_bot/scraping/action/callback.py
scraping_common_bot/scraping/action/checker.py
scraping_common_bot/scraping/action/interact.py
scraping_common_bot/scraping/collector/__init__.py
scraping_common_bot/scraping/collector/extractor.py
scraping_common_bot/scraping/loader/__init__.py
scraping_common_bot/scraping/loader/loader.py
scraping_common_bot-1.1.5.dist-info/LICENSE.txt
scraping_common_bot-1.1.5.dist-info/METADATA
scraping_common_bot-1.1.5.dist-info/WHEEL
scraping_common_bot-1.1.5.dist-info/top_level.txt
scraping_common_bot-1.1.5.dist-info/RECORD
