Metadata-Version: 2.1
Name: scraping-common-bot
Version: 1.1.5
Summary: Add a short description here!
Home-page: https://github.com/pyscaffold/pyscaffold/
Author: pancudaniel7
Author-email: pancudaniel7@gmail.com
License: MIT
Project-URL: Documentation, https://pyscaffold.org/
Platform: any
Classifier: Development Status :: 4 - Beta
Classifier: Programming Language :: Python
License-File: LICENSE.txt
Requires-Dist: selenium (==4.1.0)
Requires-Dist: bs4 (==0.0.1)
Requires-Dist: logger (==1.4)
Requires-Dist: beautifulsoup4 (==4.10.0)
Requires-Dist: lxml (==4.7.1)
Requires-Dist: requests (==2.26.0)
Requires-Dist: pylint (==2.12.2)
Requires-Dist: importlib-metadata ; python_version < "3.8"
Provides-Extra: testing
Requires-Dist: setuptools ; extra == 'testing'
Requires-Dist: pytest ; extra == 'testing'
Requires-Dist: pytest-cov ; extra == 'testing'
